sqlScanner/__init__.py
sqlScanner-1.0.2.dist-info/METADATA
sqlScanner-1.0.2.dist-info/RECORD
sqlScanner-1.0.2.dist-info/WHEEL
sqlScanner-1.0.2.dist-info/top_level.txt
