Metadata-Version: 2.1
Name: sqlScanner
Version: 1.0.2
Summary: Scans .db-files for SQL tables.
Home-page: https://github.com/letsCodeMyLife/sqlScanner
Author: Henning Arvid Ladewig
Author-email: anne@opentrash.com
License: UNKNOWN
Platform: UNKNOWN
